parse_tree/__init__.py
parse_tree/frontend/build/asset-manifest.json
parse_tree/frontend/build/bootstrap.min.css
parse_tree/frontend/build/index.html
parse_tree/frontend/build/precache-manifest.860702dd11d39912206728a266996559.js
parse_tree/frontend/build/precache-manifest.86212e791c59ae08da83ec87f70e0b34.js
parse_tree/frontend/build/service-worker.js
parse_tree/frontend/build/static/css/main.33d8ae6b.chunk.css
parse_tree/frontend/build/static/css/main.33d8ae6b.chunk.css.map
parse_tree/frontend/build/static/css/main.4363a527.chunk.css
parse_tree/frontend/build/static/css/main.4363a527.chunk.css.map
parse_tree/frontend/build/static/js/2.3558ddb7.chunk.js
parse_tree/frontend/build/static/js/2.3558ddb7.chunk.js.LICENSE.txt
parse_tree/frontend/build/static/js/2.3558ddb7.chunk.js.map
parse_tree/frontend/build/static/js/main.53bd2766.chunk.js
parse_tree/frontend/build/static/js/main.53bd2766.chunk.js.map
parse_tree/frontend/build/static/js/main.5f2941a4.chunk.js
parse_tree/frontend/build/static/js/main.5f2941a4.chunk.js.map
parse_tree/frontend/build/static/js/runtime-main.79f62daa.js
parse_tree/frontend/build/static/js/runtime-main.79f62daa.js.map
parse_tree_component/__init__.py
parse_tree_component/frontend/build/asset-manifest.json
parse_tree_component/frontend/build/bootstrap.min.css
parse_tree_component/frontend/build/index.html
parse_tree_component/frontend/build/precache-manifest.197e085a793757985546f01925edc320.js
parse_tree_component/frontend/build/precache-manifest.ce7befaa52ea0bb4d967354e4692db7e.js
parse_tree_component/frontend/build/service-worker.js
parse_tree_component/frontend/build/static/css/main.4363a527.chunk.css
parse_tree_component/frontend/build/static/css/main.4363a527.chunk.css.map
parse_tree_component/frontend/build/static/css/main.feec66a8.chunk.css
parse_tree_component/frontend/build/static/css/main.feec66a8.chunk.css.map
parse_tree_component/frontend/build/static/js/2.285f28fb.chunk.js
st_parsetree-0.0.2.dist-info/LICENSE
st_parsetree-0.0.2.dist-info/METADATA
st_parsetree-0.0.2.dist-info/WHEEL
st_parsetree-0.0.2.dist-info/top_level.txt
st_parsetree-0.0.2.dist-info/RECORD
